odoo/addons/hr_timesheet_name_customer/README.rst
odoo/addons/hr_timesheet_name_customer/__init__.py
odoo/addons/hr_timesheet_name_customer/__manifest__.py
odoo/addons/hr_timesheet_name_customer/i18n/es.po
odoo/addons/hr_timesheet_name_customer/i18n/fr.po
odoo/addons/hr_timesheet_name_customer/i18n/hr_timesheet_name_customer.pot
odoo/addons/hr_timesheet_name_customer/i18n/it.po
odoo/addons/hr_timesheet_name_customer/i18n/pt_BR.po
odoo/addons/hr_timesheet_name_customer/models/__init__.py
odoo/addons/hr_timesheet_name_customer/models/hr_timesheet_name_customer.py
odoo/addons/hr_timesheet_name_customer/readme/CONFIGURE.md
odoo/addons/hr_timesheet_name_customer/readme/CONTEXT.md
odoo/addons/hr_timesheet_name_customer/readme/DESCRIPTION.md
odoo/addons/hr_timesheet_name_customer/readme/HISTORY.md
odoo/addons/hr_timesheet_name_customer/readme/USAGE.md
odoo/addons/hr_timesheet_name_customer/report/name_customer_template.xml
odoo/addons/hr_timesheet_name_customer/static/description/icon.png
odoo/addons/hr_timesheet_name_customer/static/description/index.html
odoo/addons/hr_timesheet_name_customer/tests/__init__.py
odoo/addons/hr_timesheet_name_customer/tests/common.py
odoo/addons/hr_timesheet_name_customer/tests/test_name_customer.py
odoo/addons/hr_timesheet_name_customer/views/hr_timesheet_name_customer_views.xml
odoo/addons/hr_timesheet_name_customer/views/project_portal_templates.xml
odoo_addon_hr_timesheet_name_customer-18.0.1.0.0.3.dist-info/METADATA
odoo_addon_hr_timesheet_name_customer-18.0.1.0.0.3.dist-info/WHEEL
odoo_addon_hr_timesheet_name_customer-18.0.1.0.0.3.dist-info/top_level.txt
odoo_addon_hr_timesheet_name_customer-18.0.1.0.0.3.dist-info/RECORD
