Metadata-Version: 2.1
Name: odoo-addon-hr_timesheet_name_customer
Version: 18.0.1.0.0.3
Requires-Python: >=3.10
Requires-Dist: odoo==18.0.*
Summary: Add 'Description Customer' field for timesheets
Home-page: https://github.com/OCA/timesheet
License: LGPL-3
Author: Odoo Community Association (OCA), Cetmix
Author-email: support@odoo-community.org
Classifier: Programming Language :: Python
Classifier: Framework :: Odoo
Classifier: Framework :: Odoo :: 18.0
Classifier: License :: OSI Approved :: GNU Lesser General Public License v3 (LGPLv3)
